fdbk_dynamodb_plugin
