Metadata-Version: 2.1
Name: fdbk-dynamodb-plugin
Version: 3.0.2
Summary: DynamoDB plugin for fdbk
Home-page: https://github.com/kangasta/fdbk_dynamodb_plugin
Author: Toni Kangas
License: UNKNOWN
Platform: UNKNOWN
Classifier: Programming Language :: Python :: 3
Classifier: License :: OSI Approved :: MIT License
Classifier: Operating System :: OS Independent
Requires-Python: >=3.6
